[
    {
        "name": "pari acess last",
        "email_id": "parikannappan@gmail.com",
        "organisation": "TCS",
        "check_in_time": "2019-09-05 11:00:52.934599"
    },
    {
        "name": "kapil",
        "email_id": "dharmendra@codeops.tech",
        "organisation": "wewef",
        "check_in_time": "2019-09-05 11:02:30.508126"
    },
    {
        "name": "Dharmendra Singh Negi",
        "email_id": "dharmendra@codeops.tech",
        "organisation": "sdwefwef",
        "check_in_time": "2019-09-05 11:05:20.114714"
    },
    {
        "name": "RILIKTA NAYAK",
        "email_id": "rilikta@gmail.com",
        "organisation": "szsvff",
        "check_in_time": "2019-09-05 11:09:15.816209"
    },
    {
        "name": "Acess code test two",
        "email_id": "parikannappan@gmail.com",
        "organisation": "TCS",
        "check_in_time": "2019-09-05 11:14:41.104544"
    },
    {
        "name": "Aran",
        "email_id": "parikannappan@gmail.com",
        "organisation": "Cts",
        "check_in_time": "2019-09-05 11:22:22.989765"
    },
    {
        "name": "pari disacc",
        "email_id": "parikannappan@gmail.com",
        "organisation": "TCS",
        "check_in_time": "2019-09-05 08:47:12.694435"
    },
    {
        "name": "RILIKTA NAYAK",
        "email_id": "rilikta@gmail.com",
        "organisation": "hbevhv",
        "check_in_time": "2019-09-05 10:43:05.518575"
    },
    {
        "name": "RILIKTA NAYAK",
        "email_id": "rilikta@gmail.com",
        "organisation": "seesd",
        "check_in_time": "2019-09-05 10:45:33.481093"
    },
    {
        "name": "Mofis",
        "email_id": "parikannappan@gmail.com",
        "organisation": "CTS",
        "check_in_time": "2019-09-05 10:47:20.511069"
    },
    {
        "name": "Pari access local test",
        "email_id": "parikannappan@gmail.com",
        "organisation": "TCS",
        "check_in_time": "2019-09-05 10:52:47.520125"
    },
    {
        "name": "RILIKTA NAYAK",
        "email_id": "rilikta@gmail.com",
        "organisation": "vcdgv",
        "check_in_time": "2019-09-05 10:54:55.312661"
    },
    {
        "name": "Wawrika",
        "email_id": "parikannappan@gmail.com",
        "organisation": "CTS",
        "check_in_time": "2019-09-05 10:56:37.279100"
    },
    {
        "name": "Ritu",
        "email_id": "rilikta@gmail.com",
        "organisation": "ibdcdc",
        "check_in_time": "2019-09-05 10:58:21.894917"
    },
    {
        "name": "mohit",
        "email_id": "dharmendra@codeops.tech",
        "organisation": "wecwe",
        "check_in_time": "2019-09-05 10:59:59.816929"
    }
]